LICENSE
custom_widget_test123/__init__.py
custom_widget_test123/static/script.js
custom_widget_test123/static/styles.css
custom_widget_test123/widget.py
custom_widget_test123-0.1.2.dist-info/LICENSE
custom_widget_test123-0.1.2.dist-info/METADATA
custom_widget_test123-0.1.2.dist-info/WHEEL
custom_widget_test123-0.1.2.dist-info/RECORD
